Lobster/__init__.py
Lobster_3dEngine-0.0.1.dist-info/LICENSE.txt
Lobster_3dEngine-0.0.1.dist-info/METADATA
Lobster_3dEngine-0.0.1.dist-info/WHEEL
Lobster_3dEngine-0.0.1.dist-info/top_level.txt
Lobster_3dEngine-0.0.1.dist-info/RECORD
