Metadata-Version: 2.1
Name: Lobster-3dEngine
Version: 0.0.1
Summary: A python library purposed as a simple 3D display engine
Home-page: UNKNOWN
Author: Rushil Shah
License: UNKNOWN
Platform: UNKNOWN
Classifier: Programming Language :: Python :: 3
Classifier: License :: OSI Approved :: MIT License
Classifier: Operating System :: OS Independent
Requires-Python: >=3.5
